{"duration": 11.13310956954956, "input_args": {"X": "array([[0.        , 0.        , 0.        , ..., 0.        , 1.68949449,\n        0.90418303],\n       [0.        , 0.        , 0.        , ..., 0.90418303, 0.        ,\n        0.24124742],\n       [0.        , 0.        , 0.        , ..., 0.24124742, 0.64535987,\n        0.        ],\n       ...,\n       [0.        , 0.64981455, 0.        , ..., 0.        , 0.        ,\n        0.        ],\n       [0.        , 0.        , 0.        , ..., 0.        , 0.        ,\n        0.        ],\n       [0.        , 0.17772537, 0.        , ..., 0.        , 0.        ,\n        0.        ]])", "k": "16", "max_iter": "16", "init": "'subspaces'", "return_sse": "True"}}