{"duration": 45.076448917388916, "input_args": {"X": "array([[0.        , 0.        , 0.        , 0.        , 0.        ],\n       [0.        , 0.        , 0.        , 0.        , 2.15751815],\n       [0.        , 0.        , 0.        , 0.        , 1.74697542],\n       ...,\n       [1.35489976, 1.22368968, 2.15027905, 0.        , 1.44532764],\n       [2.15027905, 1.82608151, 1.82840216, 0.        , 2.05021644],\n       [1.82840216, 0.        , 0.05820692, 0.        , 2.02589083]])", "k": "32", "max_iter": "16", "init": "'subspaces'", "return_sse": "True"}}