{"duration": 316.70334124565125, "input_args": {"X": "array([[0.        , 0.        , 0.        , ..., 0.        , 0.0138917 ,\n        0.        ],\n       [0.        , 0.        , 0.        , ..., 0.0138917 , 0.        ,\n        1.04660976],\n       [0.        , 0.        , 0.        , ..., 0.        , 1.04660976,\n        0.        ],\n       ...,\n       [0.        , 0.77392787, 0.        , ..., 0.        , 0.        ,\n        0.        ],\n       [0.77392787, 0.        , 0.        , ..., 0.        , 0.        ,\n        0.        ],\n       [0.        , 0.        , 0.        , ..., 0.        , 0.        ,\n        0.        ]])", "k": "256", "max_iter": "16", "init": "'subspaces'", "return_sse": "True"}}