{"duration": 14.802688598632812, "input_args": {"X": "array([[0.        , 0.        , 0.        , 0.        , 0.        ],\n       [0.        , 0.        , 0.        , 0.        , 4.45538759],\n       [0.        , 0.        , 0.        , 0.        , 3.27686048],\n       ...,\n       [0.        , 0.44791096, 0.90766543, 0.59688783, 1.00626993],\n       [0.        , 0.59688783, 0.        , 0.        , 0.797809  ],\n       [0.        , 0.        , 0.        , 0.        , 0.        ]])", "k": "64", "max_iter": "16", "init": "'subspaces'", "return_sse": "True"}}