{"duration": 15.79565691947937, "input_args": {"X": "array([[0.        , 0.        , 0.        , ..., 0.        , 0.        ,\n        1.1955086 ],\n       [0.        , 0.        , 0.        , ..., 0.        , 1.1955086 ,\n        0.65968692],\n       [0.        , 0.        , 0.        , ..., 1.1955086 , 0.65968692,\n        0.        ],\n       ...,\n       [0.        , 0.        , 1.25932229, ..., 0.        , 0.        ,\n        0.        ],\n       [0.        , 1.25932229, 0.41178304, ..., 0.        , 0.        ,\n        0.        ],\n       [1.25932229, 0.41178304, 0.        , ..., 0.        , 0.        ,\n        0.        ]])", "k": "256", "max_iter": "16", "init": "'subspaces'", "return_sse": "True"}}