{"duration": 4.081257343292236, "input_args": {"X": "array([[0.        , 0.        , 0.        , ..., 0.        , 1.01048946,\n        0.        ],\n       [0.        , 0.        , 0.        , ..., 1.01048946, 0.        ,\n        0.        ],\n       [0.        , 0.        , 0.        , ..., 0.        , 0.        ,\n        0.        ],\n       ...,\n       [0.        , 0.58859932, 0.        , ..., 0.        , 0.        ,\n        0.        ],\n       [0.58859932, 0.        , 0.        , ..., 0.        , 0.        ,\n        0.        ],\n       [0.        , 0.        , 0.        , ..., 0.        , 0.        ,\n        0.        ]])", "k": "32", "max_iter": "16", "init": "'subspaces'", "return_sse": "True"}}