{"duration": 49.78217911720276, "input_args": {"X": "array([[0.        , 0.        , 0.        , 0.        , 0.        ],\n       [0.        , 0.        , 0.        , 0.        , 1.91130018],\n       [0.        , 0.        , 0.        , 0.        , 0.49086058],\n       ...,\n       [0.54542994, 0.        , 0.02235495, 0.        , 0.60240161],\n       [0.02235495, 0.        , 0.        , 0.        , 0.293782  ],\n       [0.        , 0.        , 0.        , 0.        , 0.18691768]])", "k": "128", "max_iter": "16", "init": "'subspaces'", "return_sse": "True"}}