{"duration": 612.0718886852264, "input_args": {"X": "array([[0.        , 0.        , 0.        , ..., 0.        , 0.07471777,\n        0.262191  ],\n       [0.        , 0.        , 0.        , ..., 0.07471777, 0.262191  ,\n        0.35024896],\n       [0.        , 0.        , 0.        , ..., 0.262191  , 0.35024896,\n        0.20260334],\n       ...,\n       [1.11278141, 0.65387946, 0.76261765, ..., 0.        , 0.        ,\n        0.        ],\n       [0.65387946, 0.76261765, 0.55174488, ..., 0.        , 0.        ,\n        0.        ],\n       [0.76261765, 0.55174488, 0.        , ..., 0.        , 0.        ,\n        0.        ]])", "k": "64", "max_iter": "16", "init": "'subspaces'", "return_sse": "True"}}