{"duration": 13.487942934036255, "input_args": {"X": "array([[0.        , 0.        , 0.        , ..., 0.        , 0.06330894,\n        0.        ],\n       [0.        , 0.        , 0.        , ..., 0.06330894, 0.        ,\n        0.        ],\n       [0.        , 0.        , 0.        , ..., 0.        , 0.        ,\n        0.        ],\n       ...,\n       [0.        , 0.        , 0.        , ..., 0.        , 0.        ,\n        0.        ],\n       [0.        , 0.        , 0.15716472, ..., 0.        , 0.        ,\n        0.        ],\n       [0.        , 0.15716472, 0.        , ..., 0.        , 0.        ,\n        0.        ]])", "k": "64", "max_iter": "16", "init": "'subspaces'", "return_sse": "True"}}